flatprot/__init__.py
flatprot/alignment/__init__.py
flatprot/alignment/db.py
flatprot/alignment/errors.py
flatprot/alignment/foldseek.py
flatprot/alignment/utils.py
flatprot/cli/__init__.py
flatprot/cli/align.py
flatprot/cli/errors.py
flatprot/cli/main.py
flatprot/cli/overlay.py
flatprot/cli/project.py
flatprot/cli/split.py
flatprot/cli/utils.py
flatprot/core/__init__.py
flatprot/core/coordinates.py
flatprot/core/errors.py
flatprot/core/logger.py
flatprot/core/structure.py
flatprot/core/types.py
flatprot/io/__init__.py
flatprot/io/annotations.py
flatprot/io/dssp.py
flatprot/io/errors.py
flatprot/io/matrix.py
flatprot/io/structure.py
flatprot/io/structure_gemmi_adapter.py
flatprot/io/styles.py
flatprot/projection/__init__.py
flatprot/projection/base.py
flatprot/projection/orthographic.py
flatprot/renderers/__init__.py
flatprot/renderers/svg_annotations.py
flatprot/renderers/svg_renderer.py
flatprot/renderers/svg_structure.py
flatprot/scene/__init__.py
flatprot/scene/base_element.py
flatprot/scene/connection.py
flatprot/scene/errors.py
flatprot/scene/group.py
flatprot/scene/resolver.py
flatprot/scene/scene.py
flatprot/scene/annotation/__init__.py
flatprot/scene/annotation/area.py
flatprot/scene/annotation/base_annotation.py
flatprot/scene/annotation/line.py
flatprot/scene/annotation/point.py
flatprot/scene/annotation/position.py
flatprot/scene/structure/__init__.py
flatprot/scene/structure/base_structure.py
flatprot/scene/structure/coil.py
flatprot/scene/structure/helix.py
flatprot/scene/structure/sheet.py
flatprot/transformation/__init__.py
flatprot/transformation/base_transformation.py
flatprot/transformation/error.py
flatprot/transformation/inertia_transformation.py
flatprot/transformation/matrix_transformation.py
flatprot/transformation/transformation_matrix.py
flatprot/utils/__init__.py
flatprot/utils/alignment.py
flatprot/utils/database.py
flatprot/utils/domain_utils.py
flatprot/utils/overlay_utils.py
flatprot/utils/scene_utils.py
flatprot-2.4.9.dist-info/METADATA
flatprot-2.4.9.dist-info/WHEEL
flatprot-2.4.9.dist-info/entry_points.txt
flatprot-2.4.9.dist-info/licenses/LICENSE
flatprot-2.4.9.dist-info/RECORD
