Metadata-Version: 2.4
Name: FlatProt
Version: 2.4.9
Summary: Python package for creating simplified 2D protein visualizations. Specialized on showing differences and similarities between proteins of the same protein family.
Project-URL: Repository, https://github.com/t03i/FlatProt
Project-URL: Documentation, https://t03i.github.io/FlatProt/
Project-URL: Zenodo, https://doi.org/10.5281/zenodo.15264810
Author-email: Tobias O <tobias.olenyi@tum.de>, Constantin C <ge37goy@mytum.de>
License-Expression: Apache-2.0
License-File: LICENSE
Requires-Python: <3.14,>=3.11
Requires-Dist: cairosvg>=2.8.2
Requires-Dist: cyclopts>=3.9.0
Requires-Dist: drawsvg[all]>=2.4.0
Requires-Dist: gemmi>=0.7.0
Requires-Dist: h5py>=3.13.0
Requires-Dist: httpx>=0.28.0
Requires-Dist: numpy>=1.26.4
Requires-Dist: numpydantic>=1.6.8
Requires-Dist: platformdirs>=4.3.6
Requires-Dist: polars>=1.17.1
Requires-Dist: pydantic-extra-types>=2.10.1
Requires-Dist: pydantic-settings>=2.6.1
Requires-Dist: pydantic>=2.10.3
Requires-Dist: toml>=0.10.2
Requires-Dist: tqdm>=4.67.1
